hm_render_mapnik/__init__.py
hm_render_mapnik/hm_render_mapnik.py
hm_render_mapnik-0.0.2.dist-info/LICENSE
hm_render_mapnik-0.0.2.dist-info/METADATA
hm_render_mapnik-0.0.2.dist-info/WHEEL
hm_render_mapnik-0.0.2.dist-info/entry_points.txt
hm_render_mapnik-0.0.2.dist-info/top_level.txt
hm_render_mapnik-0.0.2.dist-info/RECORD
