Metadata-Version: 2.1
Name: hm-render-mapnik
Version: 0.0.2
Summary: Render a map for a given area to paper using mapnik
Home-page: https://github.com/roelderickx/hm-render-mapnik
Author: Roel Derickx
Author-email: hikingmap.pypi@derickx.be
License: GNU General Public License (GNU GPL v3 or above)
Platform: UNKNOWN
Classifier: Environment :: Console
Classifier: Topic :: Scientific/Engineering :: GIS
Classifier: Development Status :: 5 - Production/Stable
Classifier: Programming Language :: Python :: 3
Classifier: License :: OSI Approved :: GNU General Public License (GPL)
Classifier: Operating System :: OS Independent
Requires-Python: >=3.7
Requires-Dist: mapnik (>=0.1)
